rubibot/__init__.py
rubibot/helper.py
rubibot/types.py
pyrubikabotapi-0.0.1.dist-info/LICENCE
pyrubikabotapi-0.0.1.dist-info/METADATA
pyrubikabotapi-0.0.1.dist-info/WHEEL
pyrubikabotapi-0.0.1.dist-info/top_level.txt
pyrubikabotapi-0.0.1.dist-info/RECORD
