Metadata-Version: 2.1
Name: PyRubikaBotAPI
Version: 0.0.1
Summary: A Python library to send messages and files via Eitaa API
Home-page: https://github.com/alireza-sadeghian/EitaaSender
Author: Alireza Sadeghian
Author-email: alireza.amid110@gmail.com
License: MIT
Classifier: Programming Language :: Python :: 3
Classifier: License :: OSI Approved :: MIT License
Classifier: Operating System :: OS Independent
Requires-Python: >=3.10
License-File: LICENCE
Requires-Dist: requests
